{
  "tree": {
    "entries": [
      {
        "path": "_scheduler",
        "value": {
          "entries": [
            {
              "path": ".component",
              "mode": "100644",
              "type": "Blob",
              "value": {
                "contents": "{\"pkg\":\"[\\\"_scheduler\\\"]\",\"snapshotFormatVersion\":\"0.1\",\"isRootDataStore\":true}",
                "encoding": "utf-8"
              }
            },
            {
              "path": "663b111f-01a9-4a53-b557-a2ef7502ecc0",
              "value": {
                "entries": [
                  {
                    "path": ".attributes",
                    "mode": "100644",
                    "type": "Blob",
                    "value": {
                      "contents": "{\"type\":\"https://graph.microsoft.com/types/consensus-register-collection\"}",
                      "encoding": "utf-8"
                    }
                  },
                  {
                    "path": "header",
                    "mode": "100644",
                    "type": "Blob",
                    "value": {
                      "contents": "{\"leader\":{\"atomic\":{\"sequenceNumber\":2998,\"value\":{\"type\":\"Plain\",\"value\":null}},\"versions\":[{\"sequenceNumber\":2998,\"value\":{\"type\":\"Plain\",\"value\":null}}]}}",
                      "encoding": "utf-8"
                    }
                  }
                ]
              },
              "mode": "040000",
              "type": "Tree"
            },
            {
              "path": "gc",
              "mode": "100644",
              "type": "Blob",
              "value": {
                "contents": "{\"usedRoutes\":[\"\"],\"gcData\":{\"gcNodes\":{\"/root\":[\"/_scheduler/663b111f-01a9-4a53-b557-a2ef7502ecc0\",\"/_scheduler\"],\"/663b111f-01a9-4a53-b557-a2ef7502ecc0\":[\"/_scheduler\"],\"/\":[\"/_scheduler/root\",\"/_scheduler/663b111f-01a9-4a53-b557-a2ef7502ecc0\"]}}}",
                "encoding": "utf-8"
              }
            },
            {
              "path": "root",
              "value": {
                "entries": [
                  {
                    "path": ".attributes",
                    "mode": "100644",
                    "type": "Blob",
                    "value": {
                      "contents": "{\"type\":\"https://graph.microsoft.com/types/map\"}",
                      "encoding": "utf-8"
                    }
                  },
                  {
                    "path": "header",
                    "mode": "100644",
                    "type": "Blob",
                    "value": {
                      "contents": "{\"blobs\":[],\"content\":{\"scheduler\":{\"type\":\"Plain\",\"value\":{\"type\":\"__fluid_handle__\",\"url\":\"/_scheduler/663b111f-01a9-4a53-b557-a2ef7502ecc0\"}}}}",
                      "encoding": "utf-8"
                    }
                  }
                ]
              },
              "mode": "040000",
              "type": "Tree"
            }
          ]
        },
        "mode": "040000",
        "type": "Tree"
      },
      {
        "mode": "100644",
        "path": ".attributes",
        "type": "Blob",
        "value": {
          "contents": "{\"branch\":\"FileStorageDocId\",\"minimumSequenceNumber\":2997,\"sequenceNumber\":3000,\"term\":1}",
          "encoding": "utf-8"
        }
      },
      {
        "path": "atMentions",
        "value": {
          "entries": [
            {
              "path": ".component",
              "mode": "100644",
              "type": "Blob",
              "value": {
                "contents": "{\"pkg\":\"[\\\"@ms/atmentions\\\"]\",\"snapshotFormatVersion\":\"0.1\",\"isRootDataStore\":true}",
                "encoding": "utf-8"
              }
            },
            {
              "path": "gc",
              "mode": "100644",
              "type": "Blob",
              "value": {
                "contents": "{\"usedRoutes\":[\"\"],\"gcData\":{\"gcNodes\":{\"/instances\":[\"/atMentions\"],\"/\":[\"/atMentions/instances\"]}}}",
                "encoding": "utf-8"
              }
            },
            {
              "path": "instances",
              "value": {
                "entries": [
                  {
                    "path": ".attributes",
                    "mode": "100644",
                    "type": "Blob",
                    "value": {
                      "contents": "{\"type\":\"https://graph.microsoft.com/types/map\"}",
                      "encoding": "utf-8"
                    }
                  },
                  {
                    "path": "header",
                    "mode": "100644",
                    "type": "Blob",
                    "value": {
                      "contents": "{\"blobs\":[],\"content\":{}}",
                      "encoding": "utf-8"
                    }
                  }
                ]
              },
              "mode": "040000",
              "type": "Tree"
            }
          ]
        },
        "mode": "040000",
        "type": "Tree"
      },
      {
        "path": "catalog",
        "value": {
          "entries": [
            {
              "path": ".component",
              "mode": "100644",
              "type": "Blob",
              "value": {
                "contents": "{\"pkg\":\"[\\\"@ms/catalog\\\"]\",\"snapshotFormatVersion\":\"0.1\",\"isRootDataStore\":true}",
                "encoding": "utf-8"
              }
            },
            {
              "path": "gc",
              "mode": "100644",
              "type": "Blob",
              "value": {
                "contents": "{\"usedRoutes\":[\"\"],\"gcData\":{\"gcNodes\":{\"/\":[]}}}",
                "encoding": "utf-8"
              }
            }
          ]
        },
        "mode": "040000",
        "type": "Tree"
      },
      {
        "path": "defaultComponent",
        "value": {
          "entries": [
            {
              "path": ".component",
              "mode": "100644",
              "type": "Blob",
              "value": {
                "contents": "{\"pkg\":\"[\\\"@ms/scriptor\\\"]\",\"snapshotFormatVersion\":\"0.1\",\"isRootDataStore\":true}",
                "encoding": "utf-8"
              }
            },
            {
              "path": "031285c0-a9f4-4f3c-b78f-cf6d90cc374c",
              "value": {
                "entries": [
                  {
                    "path": ".attributes",
                    "mode": "100644",
                    "type": "Blob",
                    "value": {
                      "contents": "{\"type\":\"https://graph.microsoft.com/types/map\",\"snapshotFormatVersion\":\"0.2\",\"packageVersion\":\"0.35.0\"}",
                      "encoding": "utf-8"
                    }
                  },
                  {
                    "path": "header",
                    "mode": "100644",
                    "type": "Blob",
                    "value": {
                      "contents": "{\"blobs\":[],\"content\":{\"ItemType\":{\"type\":\"Plain\",\"value\":\"Style\"},\"name\":{\"type\":\"Plain\",\"value\":\"Emphasis\"},\"styleTarget\":{\"type\":\"Plain\",\"value\":\"character\"},\"propertiesitalic\":{\"type\":\"Plain\",\"value\":true}}}",
                      "encoding": "utf-8"
                    }
                  }
                ]
              },
              "mode": "040000",
              "type": "Tree"
            },
            {
              "path": "0e81569f-f59f-4102-b69e-8bfcf5e2301e",
              "value": {
                "entries": [
                  {
                    "path": ".attributes",
                    "mode": "100644",
                    "type": "Blob",
                    "value": {
                      "contents": "{\"type\":\"https://graph.microsoft.com/types/map\",\"snapshotFormatVersion\":\"0.2\",\"packageVersion\":\"0.35.0\"}",
                      "encoding": "utf-8"
                    }
                  },
                  {
                    "path": "header",
                    "mode": "100644",
                    "type": "Blob",
                    "value": {
                      "contents": "{\"blobs\":[],\"content\":{\"ItemType\":{\"type\":\"Plain\",\"value\":\"Style\"},\"name\":{\"type\":\"Plain\",\"value\":\"Fixed Table\"},\"styleTarget\":{\"type\":\"Plain\",\"value\":\"table\"},\"propertiestableColumnWidth\":{\"type\":\"Plain\",\"value\":100},\"propertiesbold\":{\"type\":\"Plain\",\"value\":true}}}",
                      "encoding": "utf-8"
                    }
                  }
                ]
              },
              "mode": "040000",
              "type": "Tree"
            },
            {
              "path": "115d8655-0c3c-43d2-a15f-52d77fd3c918",
              "value": {
                "entries": [
                  {
                    "path": ".attributes",
                    "mode": "100644",
                    "type": "Blob",
                    "value": {
                      "contents": "{\"type\":\"https://graph.microsoft.com/types/map\",\"snapshotFormatVersion\":\"0.2\",\"packageVersion\":\"0.35.0\"}",
                      "encoding": "utf-8"
                    }
                  },
                  {
                    "path": "header",
                    "mode": "100644",
                    "type": "Blob",
                    "value": {
                      "contents": "{\"blobs\":[],\"content\":{\"ItemType\":{\"type\":\"Plain\",\"value\":\"Style\"},\"name\":{\"type\":\"Plain\",\"value\":\"Heading 2\"},\"styleTarget\":{\"type\":\"Plain\",\"value\":\"paragraph\"},\"propertiesfontName\":{\"type\":\"Plain\",\"value\":\"Segoe UI\"},\"propertiesbold\":{\"type\":\"Plain\",\"value\":true},\"propertiesfontSize\":{\"type\":\"Plain\",\"value\":18},\"propertiesfontColor\":{\"type\":\"Plain\",\"value\":\"#484644\"},\"propertiespaddingBottom\":{\"type\":\"Plain\",\"value\":15},\"propertiespaddingTop\":{\"type\":\"Plain\",\"value\":12},\"propertiesrole\":{\"type\":\"Plain\",\"value\":\"heading\"},\"propertiesariaLevel\":{\"type\":\"Plain\",\"value\":\"2\"},\"propertiestabIndex\":{\"type\":\"Plain\",\"value\":-1},\"propertiesoutline\":{\"type\":\"Plain\",\"value\":\"none\"}}}",
                      "encoding": "utf-8"
                    }
                  }
                ]
              },
              "mode": "040000",
              "type": "Tree"
            },
            {
              "path": "179fb24a-1187-45eb-8330-5c3e3b6b2598",
              "value": {
                "entries": [
                  {
                    "path": ".attributes",
                    "mode": "100644",
                    "type": "Blob",
                    "value": {
                      "contents": "{\"type\":\"https://graph.microsoft.com/types/map\",\"snapshotFormatVersion\":\"0.2\",\"packageVersion\":\"0.35.0\"}",
                      "encoding": "utf-8"
                    }
                  },
                  {
                    "path": "header",
                    "mode": "100644",
                    "type": "Blob",
                    "value": {
                      "contents": "{\"blobs\":[],\"content\":{\"ItemType\":{\"type\":\"Plain\",\"value\":\"ListRegistry\"},\"listRegistryList-83\":{\"type\":\"Plain\",\"value\":{\"type\":\"__fluid_handle__\",\"url\":\"/defaultComponent/90e448c6-8d29-4e56-bf6d-126423b700a5\"}},\"listRegistryList111\":{\"type\":\"Plain\",\"value\":{\"type\":\"__fluid_handle__\",\"url\":\"/defaultComponent/23785c73-3f07-4064-8505-5f3ea078a3f3\"}},\"listRegistryList0\":{\"type\":\"Plain\",\"value\":{\"type\":\"__fluid_handle__\",\"url\":\"/defaultComponent/7af81df4-4161-4438-ab89-a68863b3cd1d\"}}}}",
                      "encoding": "utf-8"
                    }
                  }
                ]
              },
              "mode": "040000",
              "type": "Tree"
            },
            {
              "path": "1c868c2e-38a9-4c69-bd74-a461e644ecb6",
              "value": {
                "entries": [
                  {
                    "path": ".attributes",
                    "mode": "100644",
                    "type": "Blob",
                    "value": {
                      "contents": "{\"type\":\"https://graph.microsoft.com/types/mergeTree\",\"snapshotFormatVersion\":\"0.1\",\"packageVersion\":\"0.35.0\"}",
                      "encoding": "utf-8"
                    }
                  },
                  {
                    "path": "content",
                    "value": {
                      "entries": [
                        {
                          "path": "header",
                          "mode": "100644",
                          "type": "Blob",
                          "value": {
                            "contents": "{\"chunkStartSegmentIndex\":0,\"chunkSegmentCount\":31,\"chunkLengthChars\":1544,\"totalLengthChars\":1544,\"totalSegmentCount\":31,\"chunkSequenceNumber\":2997,\"segmentTexts\":[{\"text\":\"56d6lfl9inhjepv3nb3u2fkfxe793c0q3dmsmlr8tt9i\",\"props\":{\"{00000000-0000-0835-0000-000000000000}\":false,\"{00000000-0000-2a0c-0000-000000000000}\":\"\"}},{\"marker\":{\"refType\":1},\"props\":{\"referenceTileLabels\":[\"Eop\"],\"markerId\":\"6b477c23-11b7-417e-af03-6b761045b887\",\"ItemType\":\"Paragraph\",\"Properties\":{\"isRtl\":false,\"bold\":false,\"highlight\":\"\"}}},{\"text\":\"hqxdz3p2azke7mfzwwlkx7gjbycjzv4jrff42jsimic5wy0gf3o9j87pznl12v13ftchbkyxccumwsea4910ovxp4imprh1p3n46nq7efs104mglrx9esvsvkc1igw3sooqaogvnz1wqehizthcal9gyqgqmzw3jkr6s9yykl1cfb5gsp2vj5geg2g2vfdw5iebm9ovj8cz9ql5dqjqhgef1georplgkelyl6ok8zhofv00\",\"props\":{\"{00000000-0000-0835-0000-000000000000}\":false,\"{00000000-0000-2a0c-0000-000000000000}\":\"#ffffff\"}},{\"marker\":{\"refType\":1},\"props\":{\"referenceTileLabels\":[\"Eop\"],\"markerId\":\"ed1d89a5-3517-418f-aadf-98e4acae534b\",\"ItemType\":\"Paragraph\",\"Properties\":{\"isRtl\":false,\"bold\":false,\"highlight\":\"#ffffff\",\"listItemFormatIndex\":0,\"listId\":\"listRegistryList-83\"}}},{\"text\":\"s5kfs8zh6ip5n9js5zcs0mf0ju1jv4zq5e4ldjdk8kzono3sgv8o59lx1xnvi296nzlke7c4omdrydudh50573rsx2mobsacaz7rozm6wjy50qfasljwneu7dzhdczpw86zaeu7vt2fr1uaks94srl7ojal4idh8b5x05wqaji87ixrd1hvlbx4q1dba1fcm15ge2t3i6zwx1dl40bsw7itxdxxqg8cd1zl7amn1lom6c1\",\"props\":{\"{00000000-0000-0835-0000-000000000000}\":false,\"{00000000-0000-2a0c-0000-000000000000}\":\"\"}},{\"marker\":{\"refType\":1},\"props\":{\"referenceTileLabels\":[\"Eop\"],\"markerId\":\"dfbe20a1-22d0-46b4-9f25-f9814aae626f\",\"ItemType\":\"Paragraph\",\"Properties\":{\"isRtl\":false,\"bold\":false,\"highlight\":\"#ffffff\",\"listItemFormatIndex\":1,\"listId\":\"listRegistryList-83\"}}},{\"text\":\"s669uj7vdvqc5jh9pv6zud6rgojr1ltc3jkv5idju\",\"props\":{\"{00000000-0000-0835-0000-000000000000}\":false,\"{00000000-0000-2a0c-0000-000000000000}\":\"\"}},{\"marker\":{\"refType\":1},\"props\":{\"referenceTileLabels\":[\"Eop\"],\"markerId\":\"5ef0ec0a-9cf8-48e1-82a7-ff05413ed832\",\"ItemType\":\"Paragraph\",\"Properties\":{\"isRtl\":false,\"bold\":false,\"highlight\":\"\",\"listItemFormatIndex\":0,\"listId\":\"listRegistryList-83\"}}},{\"text\":\"c\",\"props\":{\"{00000000-0000-0835-0000-000000000000}\":false,\"{00000000-0000-2a0c-0000-000000000000}\":\"#ffffff\"}},{\"text\":\"b8u5md3rkmqf7je9g2781ko5yqdeixkbswu216hdoi9qqoy7y54xwwl9yqlldqzpkpbfgfz11v6un6rxz39tk64wrn4i7h5onjkhcr76czzr5mzh5n70i3rea455hb69hstwf8ctkrkwkesxiefk1tp4numn9nrrhpseikz4b6is5hm48rapg7w6vizqaaf1szz3vul5mhrvkmsm87pdtnil9j73dvvsc0hlibb8dn2rqhxgwegb6kp7djqwy\",\"props\":{\"{00000000-0000-0835-0000-000000000000}\":false,\"{00000000-0000-2a0c-0000-000000000000}\":\"\"}},{\"marker\":{\"refType\":1},\"props\":{\"referenceTileLabels\":[\"Eop\"],\"markerId\":\"ab97d858-8e01-458b-a8b0-ca869a7cc443\",\"ItemType\":\"Paragraph\",\"Properties\":{\"isRtl\":false,\"bold\":false,\"highlight\":\"\",\"listItemFormatIndex\":0,\"listId\":\"listRegistryList-83\"}}},{\"text\":\"jqv0rzdac8\",\"props\":{\"{00000000-0000-0835-0000-000000000000}\":false,\"{00000000-0000-2a0c-0000-000000000000}\":\"\"}},\"212\",{\"text\":\"zjrb1nnziirdze5brwuvile8xuq49yl7pjq4ql8fs4tomkdu1p5npp6716euwqbizimpyh5gxo70psbgjp9suy4qmqldin55km7ah43nhfafxin1a7wx4x7f85u3tzp\",\"props\":{\"{00000000-0000-0835-0000-000000000000}\":false}},{\"marker\":{\"refType\":1},\"props\":{\"referenceTileLabels\":[\"Eop\"],\"markerId\":\"0d70c410-3762-4dca-a4c7-81cdb3b3a9c9\",\"ItemType\":\"Paragraph\",\"Properties\":{\"isRtl\":false,\"bold\":false,\"highlight\":\"\",\"listItemFormatIndex\":1,\"listId\":\"listRegistryList-83\"}}},{\"text\":\"ykyzig02n5s1gwitk4eo4wcxdutq74iai101p1dj350kv473d\",\"props\":{\"{00000000-0000-0835-0000-000000000000}\":false,\"{00000000-0000-2a0c-0000-000000000000}\":\"\"}},{\"marker\":{\"refType\":1},\"props\":{\"referenceTileLabels\":[\"Eop\"],\"markerId\":\"7601f953-36bf-4c7f-b1b7-bffbd83612b5\",\"ItemType\":\"Paragraph\",\"Properties\":{\"isRtl\":false,\"bold\":false,\"highlight\":\"\",\"listItemFormatIndex\":0,\"listId\":\"listRegistryList-83\"}}},{\"text\":\"8fa6jsw8ct\",\"props\":{\"{00000000-0000-0835-0000-000000000000}\":false,\"{00000000-0000-2a0c-0000-000000000000}\":\"\"}},\"wxx84rttyaf0pcvm78ule0riz\",{\"text\":\"3gn688gh80pqy2gsmwpkn1gvnr8zk2v45d7r19r19c9dm0wz64rukgydxm1i9gj92exwgidmtbu29r9v2l3t3fajmn1eofrz25tavkgk02xtw6ghx8pekju6h1ddlrw3v\",\"props\":{\"{00000000-0000-0835-0000-000000000000}\":false}},{\"marker\":{\"refType\":1},\"props\":{\"referenceTileLabels\":[\"Eop\"],\"markerId\":\"34d04099-a6ed-4a1b-a458-6afb204c23a7\",\"ItemType\":\"Paragraph\",\"Properties\":{\"isRtl\":false,\"bold\":false,\"highlight\":\"\",\"listItemFormatIndex\":1,\"listId\":\"listRegistryList-83\"}}},{\"text\":\"2np78oiuk75b24uzlmw1rwmdzsf1b98vyx9say9bb5a5ubiztqo21r6syth0n2vikvr8hxc\",\"props\":{}},{\"marker\":{\"refType\":1},\"props\":{\"referenceTileLabels\":[\"Eop\"],\"markerId\":\"4128c8d0-bd44-4927-9192-ee97b90542ab\",\"ItemType\":\"Paragraph\",\"Properties\":{\"isRtl\":false,\"listItemFormatIndex\":0,\"listId\":\"listRegistryList-83\"}}},{\"marker\":{\"refType\":1},\"props\":{\"referenceTileLabels\":[\"Eop\"],\"markerId\":\"0d6b8e11-9546-4f46-a25d-0b8244fe5922\",\"ItemType\":\"Paragraph\"}},\"hfds38b5rcu7kj05yrd55k9i6x6oe9e1vrc\",{\"marker\":{\"refType\":1},\"props\":{\"referenceTileLabels\":[\"Eop\"],\"markerId\":\"16da6f34-e617-4a1f-a048-54979804ea46\",\"ItemType\":\"Paragraph\"}},{\"text\":\"mlap0mju6r67tjp87zo0c40jy7piy3ybpo863km7yqmcrsouiwfqkjb0rw5d1rsifg0fqhwdcojlunnzw5so3zmwut9g1uzrcgpaa2tc6i6l2n5bmj6kifbvta37tcfg6inc4lsy5tlvtn0wwvegss8hwb28jpfctr2s0npyabdx1xyadldzq71ocxtwm3x40pb0uc3m6e7upcr2wxn71w4bpf5spw46ciaj4e\",\"props\":{\"{00000000-0000-0835-0000-000000000000}\":false,\"{00000000-0000-2a0c-0000-000000000000}\":\"\"}},{\"marker\":{\"refType\":1},\"props\":{\"referenceTileLabels\":[\"Eop\"],\"markerId\":\"f7ee6110-6c77-4bf2-8bfb-39b9a0cd6743\",\"ItemType\":\"Paragraph\",\"Properties\":{\"bold\":false,\"highlight\":\"\",\"listItemFormatIndex\":0,\"listId\":\"listRegistryList0\"}}},{\"text\":\"dr8ll2q091366bi1o6j6qpf2z\",\"props\":{\"{00000000-0000-0835-0000-000000000000}\":false,\"{00000000-0000-2a0c-0000-000000000000}\":\"\"}},{\"marker\":{\"refType\":1},\"props\":{\"referenceTileLabels\":[\"Eop\"],\"markerId\":\"7a89af7d-9b96-4c9c-882b-4722459a0c7e\",\"ItemType\":\"Paragraph\",\"Properties\":{\"bold\":false,\"highlight\":\"\",\"listItemFormatIndex\":1,\"listId\":\"listRegistryList111\"}}},{\"marker\":{\"refType\":1},\"props\":{\"referenceTileLabels\":[\"Eop\"],\"markerId\":\"eb4becf5-90a5-4bf2-85b2-321c728cb6e7\",\"ItemType\":\"Paragraph\"}}],\"headerMetadata\":{\"orderedChunkMetadata\":[{\"id\":\"header\"}],\"sequenceNumber\":2997,\"totalLength\":1544,\"totalSegmentCount\":31}}",
                            "encoding": "utf-8"
                          }
                        }
                      ]
                    },
                    "mode": "040000",
                    "type": "Tree"
                  },
                  {
                    "path": "header",
                    "mode": "100644",
                    "type": "Blob",
                    "value": {
                      "contents": "{\"intervalCollections\":{\"type\":\"Plain\",\"value\":{\"type\":\"__fluid_handle__\",\"url\":\"/defaultComponent/219bc753-71a8-43ee-aed4-8a71ae7eee46\"}}}",
                      "encoding": "utf-8"
                    }
                  }
                ]
              },
              "mode": "040000",
              "type": "Tree"
            },
            {
              "path": "219bc753-71a8-43ee-aed4-8a71ae7eee46",
              "value": {
                "entries": [
                  {
                    "path": ".attributes",
                    "mode": "100644",
                    "type": "Blob",
                    "value": {
                      "contents": "{\"type\":\"https://graph.microsoft.com/types/map\",\"snapshotFormatVersion\":\"0.2\",\"packageVersion\":\"0.35.0\"}",
                      "encoding": "utf-8"
                    }
                  },
                  {
                    "path": "header",
                    "mode": "100644",
                    "type": "Blob",
                    "value": {
                      "contents": "{\"blobs\":[],\"content\":{}}",
                      "encoding": "utf-8"
                    }
                  }
                ]
              },
              "mode": "040000",
              "type": "Tree"
            },
            {
              "path": "23785c73-3f07-4064-8505-5f3ea078a3f3",
              "value": {
                "entries": [
                  {
                    "path": ".attributes",
                    "mode": "100644",
                    "type": "Blob",
                    "value": {
                      "contents": "{\"type\":\"https://graph.microsoft.com/types/map\",\"snapshotFormatVersion\":\"0.2\",\"packageVersion\":\"0.35.0\"}",
                      "encoding": "utf-8"
                    }
                  },
                  {
                    "path": "header",
                    "mode": "100644",
                    "type": "Blob",
                    "value": {
                      "contents": "{\"blobs\":[],\"content\":{\"ItemType\":{\"type\":\"Plain\",\"value\":\"List\"},\"listId\":{\"type\":\"Plain\",\"value\":\"listRegistryList111\"},\"listItemFormat0\":{\"type\":\"Plain\",\"value\":\"%cssClass-scriptor-listItem-marker-bullet;%cc8226\"},\"listItemFormat1\":{\"type\":\"Plain\",\"value\":\"%cssClass-scriptor-listItem-marker-bullet;%cc111\"},\"listItemFormat2\":{\"type\":\"Plain\",\"value\":\"%cssClass-scriptor-listItem-marker-bullet;%cc168\"},\"listItemFormat3\":{\"type\":\"Plain\",\"value\":\"%cssClass-scriptor-listItem-marker-bullet;%cc8226\"},\"listItemFormat4\":{\"type\":\"Plain\",\"value\":\"%cssClass-scriptor-listItem-marker-bullet;%cc111\"},\"listItemFormat5\":{\"type\":\"Plain\",\"value\":\"%cssClass-scriptor-listItem-marker-bullet;%cc168\"},\"listItemFormat6\":{\"type\":\"Plain\",\"value\":\"%cssClass-scriptor-listItem-marker-bullet;%cc8226\"},\"listItemFormat7\":{\"type\":\"Plain\",\"value\":\"%cssClass-scriptor-listItem-marker-bullet;%cc111\"},\"listItemFormat8\":{\"type\":\"Plain\",\"value\":\"%cssClass-scriptor-listItem-marker-bullet;%cc168\"}}}",
                      "encoding": "utf-8"
                    }
                  }
                ]
              },
              "mode": "040000",
              "type": "Tree"
            },
            {
              "path": "3628d460-1875-4be9-a2be-a64320d66221",
              "value": {
                "entries": [
                  {
                    "path": ".attributes",
                    "mode": "100644",
                    "type": "Blob",
                    "value": {
                      "contents": "{\"type\":\"https://graph.microsoft.com/types/map\",\"snapshotFormatVersion\":\"0.2\",\"packageVersion\":\"0.35.0\"}",
                      "encoding": "utf-8"
                    }
                  },
                  {
                    "path": "header",
                    "mode": "100644",
                    "type": "Blob",
                    "value": {
                      "contents": "{\"blobs\":[],\"content\":{\"cbc66874-4f53-40ac-bbab-01cb0a40dfaa\":{\"type\":\"Plain\",\"value\":{\"type\":\"selection\",\"origMark\":-1,\"pos\":935,\"refSeqNumber\":21}},\"acabd2a1-5ae1-445f-8638-e0d98e42740e\":{\"type\":\"Plain\",\"value\":{\"type\":\"selection\",\"origMark\":-1,\"pos\":0,\"refSeqNumber\":108}},\"d2c7aaea-de7f-4971-9a93-6f6fa168dec7\":{\"type\":\"Plain\",\"value\":{\"type\":\"selection\",\"origMark\":-1,\"pos\":0,\"refSeqNumber\":131}},\"13a2ffa3-69ef-4b11-aa42-ab5b1badbe97\":{\"type\":\"Plain\",\"value\":{\"type\":\"selection\",\"origMark\":-1,\"pos\":910,\"refSeqNumber\":2414}},\"7c3f867c-bbdd-4a01-92fe-4e73509a312d\":{\"type\":\"Plain\",\"value\":{\"type\":\"selection\",\"origMark\":-1,\"pos\":248,\"refSeqNumber\":2427}},\"23da62c9-26dc-493a-b40f-352f4271ada9\":{\"type\":\"Plain\",\"value\":{\"type\":\"selection\",\"origMark\":-1,\"pos\":0,\"refSeqNumber\":2428}},\"2db56f27-00b9-4c6b-af11-cd8e74dad188\":{\"type\":\"Plain\",\"value\":{\"type\":\"selection\",\"origMark\":-1,\"pos\":0,\"refSeqNumber\":2446}},\"bd7f9e78-7264-49a3-8326-290a42934955\":{\"type\":\"Plain\",\"value\":{\"type\":\"selection\",\"origMark\":-1,\"pos\":392,\"refSeqNumber\":2446}},\"15539bc8-1699-48da-b3b6-4dfa781e0ff1\":{\"type\":\"Plain\",\"value\":{\"type\":\"selection\",\"origMark\":-1,\"pos\":0,\"refSeqNumber\":2472}},\"fe581761-89e2-4c66-8b4c-b0b2778a993f\":{\"type\":\"Plain\",\"value\":{\"type\":\"selection\",\"origMark\":0,\"pos\":1285,\"refSeqNumber\":2472}},\"b6f60f45-635b-41e5-b2dc-cfd0fe90ae55\":{\"type\":\"Plain\",\"value\":{\"type\":\"selection\",\"origMark\":-1,\"pos\":1285,\"refSeqNumber\":2535}},\"bc24a1db-73cc-4cd5-95d3-014ab6b42050\":{\"type\":\"Plain\",\"value\":{\"type\":\"selection\",\"origMark\":-1,\"pos\":0,\"refSeqNumber\":2535}},\"388b2129-067b-41f5-b3b0-17c4ddb1c8df\":{\"type\":\"Plain\",\"value\":{\"type\":\"selection\",\"origMark\":-1,\"pos\":0,\"refSeqNumber\":2568}},\"b1fe5ca6-a04f-4f75-9a95-7777fbc8c295\":{\"type\":\"Plain\",\"value\":{\"type\":\"selection\",\"origMark\":-1,\"pos\":0,\"refSeqNumber\":2627}},\"0d8892fe-b352-435e-ad91-aab3118f4aec\":{\"type\":\"Plain\",\"value\":{\"type\":\"selection\",\"origMark\":-1,\"pos\":0,\"refSeqNumber\":2627}},\"c0e32bc2-d7ed-4593-8e45-a368c8785fa2\":{\"type\":\"Plain\",\"value\":{\"type\":\"selection\",\"origMark\":-1,\"pos\":0,\"refSeqNumber\":2653}},\"839ac9d9-6a2b-4b05-9a08-1b200fc8a9f4\":{\"type\":\"Plain\",\"value\":{\"type\":\"selection\",\"origMark\":-1,\"pos\":0,\"refSeqNumber\":2653}},\"c2c60467-7027-4242-b61d-cdeaa9d43b3e\":{\"type\":\"Plain\",\"value\":{\"type\":\"selection\",\"origMark\":-1,\"pos\":0,\"refSeqNumber\":2653}},\"5b8a75fc-90b8-4640-89b6-79020703ad9f\":{\"type\":\"Plain\",\"value\":{\"type\":\"selection\",\"origMark\":-1,\"pos\":0,\"refSeqNumber\":2706}},\"1ce729d2-0e5d-4b48-93cb-fa99690b9fda\":{\"type\":\"Plain\",\"value\":{\"type\":\"selection\",\"origMark\":1285,\"pos\":0,\"refSeqNumber\":2710}},\"64d94b4b-a652-4d4a-aaee-c79622e63a60\":{\"type\":\"Plain\",\"value\":{\"type\":\"selection\",\"origMark\":1285,\"pos\":0,\"refSeqNumber\":2760}},\"d8203757-75e0-4f1a-aa27-9460e9b3d219\":{\"type\":\"Plain\",\"value\":{\"type\":\"selection\",\"origMark\":-1,\"pos\":0,\"refSeqNumber\":2806}},\"cadcd277-68ce-4f75-be2c-10f6cf1f56d2\":{\"type\":\"Plain\",\"value\":{\"type\":\"selection\",\"origMark\":-1,\"pos\":0,\"refSeqNumber\":2812}},\"f31be050-70a0-419e-9ac0-abca2e6ab4f0\":{\"type\":\"Plain\",\"value\":{\"type\":\"selection\",\"origMark\":-1,\"pos\":0,\"refSeqNumber\":2812}},\"5dd66663-9b8a-4e92-99fc-b63ed26c2709\":{\"type\":\"Plain\",\"value\":{\"type\":\"selection\",\"origMark\":-1,\"pos\":0,\"refSeqNumber\":2812}},\"38df52a5-a42d-4dd6-bebf-b9a81b67bff2\":{\"type\":\"Plain\",\"value\":{\"type\":\"selection\",\"origMark\":-1,\"pos\":0,\"refSeqNumber\":2812}},\"5a18c3c3-b544-4026-84e7-1304564db6ba\":{\"type\":\"Plain\",\"value\":{\"type\":\"selection\",\"origMark\":-1,\"pos\":0,\"refSeqNumber\":2849}},\"eb2c9a38-4073-44ca-986d-11321b11cf1d\":{\"type\":\"Plain\",\"value\":{\"type\":\"selection\",\"origMark\":-1,\"pos\":0,\"refSeqNumber\":2872}},\"c828bd43-9c4a-47da-857f-184a4fd10402\":{\"type\":\"Plain\",\"value\":{\"type\":\"selection\",\"origMark\":-1,\"pos\":0,\"refSeqNumber\":2872}},\"c27b4db7-40a8-47b9-9e3b-9a19a9471bf1\":{\"type\":\"Plain\",\"value\":{\"type\":\"selection\",\"origMark\":-1,\"pos\":0,\"refSeqNumber\":2897}},\"64511f20-e3c0-462d-aa10-d394be68d6fa\":{\"type\":\"Plain\",\"value\":{\"type\":\"selection\",\"origMark\":-1,\"pos\":0,\"refSeqNumber\":2909}},\"087ede46-6911-42ca-b7a7-0d8d3ad296d2\":{\"type\":\"Plain\",\"value\":{\"type\":\"selection\",\"origMark\":-1,\"pos\":0,\"refSeqNumber\":2922}},\"55600fd5-6739-4e11-9c8f-ce9025fb39e3\":{\"type\":\"Plain\",\"value\":{\"type\":\"selection\",\"origMark\":-1,\"pos\":0,\"refSeqNumber\":2937}},\"0f363c5e-720c-4be0-80b2-9bb229e80337\":{\"type\":\"Plain\",\"value\":{\"type\":\"selection\",\"origMark\":-1,\"pos\":0,\"refSeqNumber\":2945}},\"e5a0307b-5a2d-447e-87ad-79502b318be1\":{\"type\":\"Plain\",\"value\":{\"type\":\"selection\",\"origMark\":-1,\"pos\":1285,\"refSeqNumber\":2966}},\"d98521f9-c724-4333-8150-a4b4d9db0349\":{\"type\":\"Plain\",\"value\":{\"type\":\"selection\",\"origMark\":-1,\"pos\":0,\"refSeqNumber\":2978}},\"d7e3c1a2-4d06-49cd-bc4f-e889fdd47524\":{\"type\":\"Plain\",\"value\":{\"type\":\"selection\",\"origMark\":-1,\"pos\":0,\"refSeqNumber\":2993}}}}",
                      "encoding": "utf-8"
                    }
                  }
                ]
              },
              "mode": "040000",
              "type": "Tree"
            },
            {
              "path": "4acc1217-7bad-472d-892c-f691e5e38795",
              "value": {
                "entries": [
                  {
                    "path": ".attributes",
                    "mode": "100644",
                    "type": "Blob",
                    "value": {
                      "contents": "{\"type\":\"https://graph.microsoft.com/types/map\",\"snapshotFormatVersion\":\"0.2\",\"packageVersion\":\"0.35.0\"}",
                      "encoding": "utf-8"
                    }
                  },
                  {
                    "path": "header",
                    "mode": "100644",
                    "type": "Blob",
                    "value": {
                      "contents": "{\"blobs\":[],\"content\":{\"ItemType\":{\"type\":\"Plain\",\"value\":\"Style\"},\"name\":{\"type\":\"Plain\",\"value\":\"Strong\"},\"styleTarget\":{\"type\":\"Plain\",\"value\":\"character\"},\"propertiesbold\":{\"type\":\"Plain\",\"value\":true}}}",
                      "encoding": "utf-8"
                    }
                  }
                ]
              },
              "mode": "040000",
              "type": "Tree"
            },
            {
              "path": "7af81df4-4161-4438-ab89-a68863b3cd1d",
              "value": {
                "entries": [
                  {
                    "path": ".attributes",
                    "mode": "100644",
                    "type": "Blob",
                    "value": {
                      "contents": "{\"type\":\"https://graph.microsoft.com/types/map\",\"snapshotFormatVersion\":\"0.2\",\"packageVersion\":\"0.35.0\"}",
                      "encoding": "utf-8"
                    }
                  },
                  {
                    "path": "header",
                    "mode": "100644",
                    "type": "Blob",
                    "value": {
                      "contents": "{\"blobs\":[],\"content\":{\"ItemType\":{\"type\":\"Plain\",\"value\":\"List\"},\"listId\":{\"type\":\"Plain\",\"value\":\"listRegistryList0\"},\"listItemFormat0\":{\"type\":\"Plain\",\"value\":\"%cssClass-scriptor-listItem-marker-bullet;%cc8226\"},\"listItemFormat1\":{\"type\":\"Plain\",\"value\":\"%cssClass-scriptor-listItem-marker-bullet;%cc111\"},\"listItemFormat2\":{\"type\":\"Plain\",\"value\":\"%cssClass-scriptor-listItem-marker-bullet;%cc168\"},\"listItemFormat3\":{\"type\":\"Plain\",\"value\":\"%cssClass-scriptor-listItem-marker-bullet;%cc8226\"},\"listItemFormat4\":{\"type\":\"Plain\",\"value\":\"%cssClass-scriptor-listItem-marker-bullet;%cc111\"},\"listItemFormat5\":{\"type\":\"Plain\",\"value\":\"%cssClass-scriptor-listItem-marker-bullet;%cc168\"},\"listItemFormat6\":{\"type\":\"Plain\",\"value\":\"%cssClass-scriptor-listItem-marker-bullet;%cc8226\"},\"listItemFormat7\":{\"type\":\"Plain\",\"value\":\"%cssClass-scriptor-listItem-marker-bullet;%cc111\"},\"listItemFormat8\":{\"type\":\"Plain\",\"value\":\"%cssClass-scriptor-listItem-marker-bullet;%cc168\"}}}",
                      "encoding": "utf-8"
                    }
                  }
                ]
              },
              "mode": "040000",
              "type": "Tree"
            },
            {
              "path": "8204010d-bf9c-4bf6-a9bd-eccdda2d5501",
              "value": {
                "entries": [
                  {
                    "path": ".attributes",
                    "mode": "100644",
                    "type": "Blob",
                    "value": {
                      "contents": "{\"type\":\"https://graph.microsoft.com/types/map\",\"snapshotFormatVersion\":\"0.2\",\"packageVersion\":\"0.35.0\"}",
                      "encoding": "utf-8"
                    }
                  },
                  {
                    "path": "header",
                    "mode": "100644",
                    "type": "Blob",
                    "value": {
                      "contents": "{\"blobs\":[],\"content\":{\"ItemType\":{\"type\":\"Plain\",\"value\":\"Style\"},\"name\":{\"type\":\"Plain\",\"value\":\"Title\"},\"styleTarget\":{\"type\":\"Plain\",\"value\":\"paragraph\"},\"propertiesfontName\":{\"type\":\"Plain\",\"value\":\"Calibri Light\"},\"propertiesfontSize\":{\"type\":\"Plain\",\"value\":28}}}",
                      "encoding": "utf-8"
                    }
                  }
                ]
              },
              "mode": "040000",
              "type": "Tree"
            },
            {
              "path": "87d1481d-e476-43ec-8639-a271dafcf616",
              "value": {
                "entries": [
                  {
                    "path": ".attributes",
                    "mode": "100644",
                    "type": "Blob",
                    "value": {
                      "contents": "{\"type\":\"https://graph.microsoft.com/types/map\",\"snapshotFormatVersion\":\"0.2\",\"packageVersion\":\"0.35.0\"}",
                      "encoding": "utf-8"
                    }
                  },
                  {
                    "path": "header",
                    "mode": "100644",
                    "type": "Blob",
                    "value": {
                      "contents": "{\"blobs\":[],\"content\":{\"ItemType\":{\"type\":\"Plain\",\"value\":\"StyleRegistry\"},\"styleRegistryStyleHeading 1\":{\"type\":\"Plain\",\"value\":{\"type\":\"__fluid_handle__\",\"url\":\"/defaultComponent/b17a1b79-4a9c-4711-a91a-e9b738967d41\"}},\"styleRegistryStyleHeading 2\":{\"type\":\"Plain\",\"value\":{\"type\":\"__fluid_handle__\",\"url\":\"/defaultComponent/f4c3d94a-653d-4bb3-86cf-a0e9db67ab17\"}},\"styleRegistryStyleBody\":{\"type\":\"Plain\",\"value\":{\"type\":\"__fluid_handle__\",\"url\":\"/defaultComponent/c896c5c1-e463-44ac-ac8f-f8ad8ac218c4\"}},\"styleRegistryStyleStrong\":{\"type\":\"Plain\",\"value\":{\"type\":\"__fluid_handle__\",\"url\":\"/defaultComponent/4acc1217-7bad-472d-892c-f691e5e38795\"}},\"styleRegistryStyleEmphasis\":{\"type\":\"Plain\",\"value\":{\"type\":\"__fluid_handle__\",\"url\":\"/defaultComponent/031285c0-a9f4-4f3c-b78f-cf6d90cc374c\"}},\"styleRegistryStyleTitle\":{\"type\":\"Plain\",\"value\":{\"type\":\"__fluid_handle__\",\"url\":\"/defaultComponent/8204010d-bf9c-4bf6-a9bd-eccdda2d5501\"}},\"styleRegistryStyleFixed Table\":{\"type\":\"Plain\",\"value\":{\"type\":\"__fluid_handle__\",\"url\":\"/defaultComponent/c9bcf798-0f35-4a67-87be-6dd269749857\"}}}}",
                      "encoding": "utf-8"
                    }
                  }
                ]
              },
              "mode": "040000",
              "type": "Tree"
            },
            {
              "path": "90e448c6-8d29-4e56-bf6d-126423b700a5",
              "value": {
                "entries": [
                  {
                    "path": ".attributes",
                    "mode": "100644",
                    "type": "Blob",
                    "value": {
                      "contents": "{\"type\":\"https://graph.microsoft.com/types/map\",\"snapshotFormatVersion\":\"0.2\",\"packageVersion\":\"0.35.0\"}",
                      "encoding": "utf-8"
                    }
                  },
                  {
                    "path": "header",
                    "mode": "100644",
                    "type": "Blob",
                    "value": {
                      "contents": "{\"blobs\":[],\"content\":{\"ItemType\":{\"type\":\"Plain\",\"value\":\"List\"},\"listId\":{\"type\":\"Plain\",\"value\":\"listRegistryList-83\"},\"listItemFormat0\":{\"type\":\"Plain\",\"value\":\"%cssClass-scriptor-listItem-marker-bullet;%cc8226\"},\"listItemFormat1\":{\"type\":\"Plain\",\"value\":\"%cssClass-scriptor-listItem-marker-bullet;%cc111\"},\"listItemFormat2\":{\"type\":\"Plain\",\"value\":\"%cssClass-scriptor-listItem-marker-bullet;%cc168\"},\"listItemFormat3\":{\"type\":\"Plain\",\"value\":\"%cssClass-scriptor-listItem-marker-bullet;%cc8226\"},\"listItemFormat4\":{\"type\":\"Plain\",\"value\":\"%cssClass-scriptor-listItem-marker-bullet;%cc111\"},\"listItemFormat5\":{\"type\":\"Plain\",\"value\":\"%cssClass-scriptor-listItem-marker-bullet;%cc168\"},\"listItemFormat6\":{\"type\":\"Plain\",\"value\":\"%cssClass-scriptor-listItem-marker-bullet;%cc8226\"},\"listItemFormat7\":{\"type\":\"Plain\",\"value\":\"%cssClass-scriptor-listItem-marker-bullet;%cc111\"},\"listItemFormat8\":{\"type\":\"Plain\",\"value\":\"%cssClass-scriptor-listItem-marker-bullet;%cc168\"}}}",
                      "encoding": "utf-8"
                    }
                  }
                ]
              },
              "mode": "040000",
              "type": "Tree"
            },
            {
              "path": "a0284d80-3d0b-4f31-8e8b-1714c0aa1076",
              "value": {
                "entries": [
                  {
                    "path": ".attributes",
                    "mode": "100644",
                    "type": "Blob",
                    "value": {
                      "contents": "{\"type\":\"https://graph.microsoft.com/types/map\",\"snapshotFormatVersion\":\"0.2\",\"packageVersion\":\"0.35.0\"}",
                      "encoding": "utf-8"
                    }
                  },
                  {
                    "path": "header",
                    "mode": "100644",
                    "type": "Blob",
                    "value": {
                      "contents": "{\"blobs\":[],\"content\":{\"ItemType\":{\"type\":\"Plain\",\"value\":\"Style\"},\"name\":{\"type\":\"Plain\",\"value\":\"Emphasis\"},\"styleTarget\":{\"type\":\"Plain\",\"value\":\"character\"},\"propertiesitalic\":{\"type\":\"Plain\",\"value\":true}}}",
                      "encoding": "utf-8"
                    }
                  }
                ]
              },
              "mode": "040000",
              "type": "Tree"
            },
            {
              "path": "a9534c76-92ce-41d2-8682-586a4c1122ba",
              "value": {
                "entries": [
                  {
                    "path": ".attributes",
                    "mode": "100644",
                    "type": "Blob",
                    "value": {
                      "contents": "{\"type\":\"https://graph.microsoft.com/types/map\",\"snapshotFormatVersion\":\"0.2\",\"packageVersion\":\"0.35.0\"}",
                      "encoding": "utf-8"
                    }
                  },
                  {
                    "path": "header",
                    "mode": "100644",
                    "type": "Blob",
                    "value": {
                      "contents": "{\"blobs\":[],\"content\":{\"ItemType\":{\"type\":\"Plain\",\"value\":\"Style\"},\"name\":{\"type\":\"Plain\",\"value\":\"Body\"},\"styleTarget\":{\"type\":\"Plain\",\"value\":\"defaultStyle\"}}}",
                      "encoding": "utf-8"
                    }
                  }
                ]
              },
              "mode": "040000",
              "type": "Tree"
            },
            {
              "path": "b17a1b79-4a9c-4711-a91a-e9b738967d41",
              "value": {
                "entries": [
                  {
                    "path": ".attributes",
                    "mode": "100644",
                    "type": "Blob",
                    "value": {
                      "contents": "{\"type\":\"https://graph.microsoft.com/types/map\",\"snapshotFormatVersion\":\"0.2\",\"packageVersion\":\"0.35.0\"}",
                      "encoding": "utf-8"
                    }
                  },
                  {
                    "path": "header",
                    "mode": "100644",
                    "type": "Blob",
                    "value": {
                      "contents": "{\"blobs\":[],\"content\":{\"ItemType\":{\"type\":\"Plain\",\"value\":\"Style\"},\"name\":{\"type\":\"Plain\",\"value\":\"Heading 1\"},\"styleTarget\":{\"type\":\"Plain\",\"value\":\"paragraph\"},\"propertiesfontName\":{\"type\":\"Plain\",\"value\":\"Segoe UI SemiBold\"},\"propertiesfontSize\":{\"type\":\"Plain\",\"value\":24},\"propertiespaddingBottom\":{\"type\":\"Plain\",\"value\":15},\"propertiespaddingTop\":{\"type\":\"Plain\",\"value\":12},\"propertiesrole\":{\"type\":\"Plain\",\"value\":\"heading\"},\"propertiesariaLevel\":{\"type\":\"Plain\",\"value\":\"1\"},\"propertiestabIndex\":{\"type\":\"Plain\",\"value\":-1},\"propertiesoutline\":{\"type\":\"Plain\",\"value\":\"none\"}}}",
                      "encoding": "utf-8"
                    }
                  }
                ]
              },
              "mode": "040000",
              "type": "Tree"
            },
            {
              "path": "c6863402-5e81-45ac-83f3-03410e959604",
              "value": {
                "entries": [
                  {
                    "path": ".attributes",
                    "mode": "100644",
                    "type": "Blob",
                    "value": {
                      "contents": "{\"type\":\"https://graph.microsoft.com/types/map\",\"snapshotFormatVersion\":\"0.2\",\"packageVersion\":\"0.35.0\"}",
                      "encoding": "utf-8"
                    }
                  },
                  {
                    "path": "header",
                    "mode": "100644",
                    "type": "Blob",
                    "value": {
                      "contents": "{\"blobs\":[],\"content\":{\"ItemType\":{\"type\":\"Plain\",\"value\":\"Style\"},\"name\":{\"type\":\"Plain\",\"value\":\"Heading 1\"},\"styleTarget\":{\"type\":\"Plain\",\"value\":\"paragraph\"},\"propertiesfontName\":{\"type\":\"Plain\",\"value\":\"Segoe UI SemiBold\"},\"propertiesfontSize\":{\"type\":\"Plain\",\"value\":24},\"propertiespaddingBottom\":{\"type\":\"Plain\",\"value\":15},\"propertiespaddingTop\":{\"type\":\"Plain\",\"value\":12},\"propertiesrole\":{\"type\":\"Plain\",\"value\":\"heading\"},\"propertiesariaLevel\":{\"type\":\"Plain\",\"value\":\"1\"},\"propertiestabIndex\":{\"type\":\"Plain\",\"value\":-1},\"propertiesoutline\":{\"type\":\"Plain\",\"value\":\"none\"}}}",
                      "encoding": "utf-8"
                    }
                  }
                ]
              },
              "mode": "040000",
              "type": "Tree"
            },
            {
              "path": "c896c5c1-e463-44ac-ac8f-f8ad8ac218c4",
              "value": {
                "entries": [
                  {
                    "path": ".attributes",
                    "mode": "100644",
                    "type": "Blob",
                    "value": {
                      "contents": "{\"type\":\"https://graph.microsoft.com/types/map\",\"snapshotFormatVersion\":\"0.2\",\"packageVersion\":\"0.35.0\"}",
                      "encoding": "utf-8"
                    }
                  },
                  {
                    "path": "header",
                    "mode": "100644",
                    "type": "Blob",
                    "value": {
                      "contents": "{\"blobs\":[],\"content\":{\"ItemType\":{\"type\":\"Plain\",\"value\":\"Style\"},\"name\":{\"type\":\"Plain\",\"value\":\"Body\"},\"styleTarget\":{\"type\":\"Plain\",\"value\":\"defaultStyle\"}}}",
                      "encoding": "utf-8"
                    }
                  }
                ]
              },
              "mode": "040000",
              "type": "Tree"
            },
            {
              "path": "c9bcf798-0f35-4a67-87be-6dd269749857",
              "value": {
                "entries": [
                  {
                    "path": ".attributes",
                    "mode": "100644",
                    "type": "Blob",
                    "value": {
                      "contents": "{\"type\":\"https://graph.microsoft.com/types/map\",\"snapshotFormatVersion\":\"0.2\",\"packageVersion\":\"0.35.0\"}",
                      "encoding": "utf-8"
                    }
                  },
                  {
                    "path": "header",
                    "mode": "100644",
                    "type": "Blob",
                    "value": {
                      "contents": "{\"blobs\":[],\"content\":{\"ItemType\":{\"type\":\"Plain\",\"value\":\"Style\"},\"name\":{\"type\":\"Plain\",\"value\":\"Fixed Table\"},\"styleTarget\":{\"type\":\"Plain\",\"value\":\"table\"},\"propertiestableColumnWidth\":{\"type\":\"Plain\",\"value\":100},\"propertiesbold\":{\"type\":\"Plain\",\"value\":true}}}",
                      "encoding": "utf-8"
                    }
                  }
                ]
              },
              "mode": "040000",
              "type": "Tree"
            },
            {
              "path": "ccb9d801-45c5-4f53-8a55-841ae9ffc63f",
              "value": {
                "entries": [
                  {
                    "path": ".attributes",
                    "mode": "100644",
                    "type": "Blob",
                    "value": {
                      "contents": "{\"type\":\"https://graph.microsoft.com/types/map\",\"snapshotFormatVersion\":\"0.2\",\"packageVersion\":\"0.35.0\"}",
                      "encoding": "utf-8"
                    }
                  },
                  {
                    "path": "header",
                    "mode": "100644",
                    "type": "Blob",
                    "value": {
                      "contents": "{\"blobs\":[],\"content\":{\"ItemType\":{\"type\":\"Plain\",\"value\":\"Style\"},\"name\":{\"type\":\"Plain\",\"value\":\"Strong\"},\"styleTarget\":{\"type\":\"Plain\",\"value\":\"character\"},\"propertiesbold\":{\"type\":\"Plain\",\"value\":true}}}",
                      "encoding": "utf-8"
                    }
                  }
                ]
              },
              "mode": "040000",
              "type": "Tree"
            },
            {
              "path": "e3aaafa2-00ea-4b63-a6c8-79605b625b08",
              "value": {
                "entries": [
                  {
                    "path": ".attributes",
                    "mode": "100644",
                    "type": "Blob",
                    "value": {
                      "contents": "{\"type\":\"https://graph.microsoft.com/types/map\",\"snapshotFormatVersion\":\"0.2\",\"packageVersion\":\"0.35.0\"}",
                      "encoding": "utf-8"
                    }
                  },
                  {
                    "path": "header",
                    "mode": "100644",
                    "type": "Blob",
                    "value": {
                      "contents": "{\"blobs\":[],\"content\":{\"ItemType\":{\"type\":\"Plain\",\"value\":\"Style\"},\"name\":{\"type\":\"Plain\",\"value\":\"Title\"},\"styleTarget\":{\"type\":\"Plain\",\"value\":\"paragraph\"},\"propertiesfontName\":{\"type\":\"Plain\",\"value\":\"Calibri Light\"},\"propertiesfontSize\":{\"type\":\"Plain\",\"value\":28}}}",
                      "encoding": "utf-8"
                    }
                  }
                ]
              },
              "mode": "040000",
              "type": "Tree"
            },
            {
              "path": "e9530f65-4ea9-4c74-8724-b888bd929c65",
              "value": {
                "entries": [
                  {
                    "path": ".attributes",
                    "mode": "100644",
                    "type": "Blob",
                    "value": {
                      "contents": "{\"type\":\"https://graph.microsoft.com/types/map\",\"snapshotFormatVersion\":\"0.2\",\"packageVersion\":\"0.35.0\"}",
                      "encoding": "utf-8"
                    }
                  },
                  {
                    "path": "header",
                    "mode": "100644",
                    "type": "Blob",
                    "value": {
                      "contents": "{\"blobs\":[],\"content\":{\"ItemType\":{\"type\":\"Plain\",\"value\":\"StyleRegistry\"},\"styleRegistryStyleHeading 1\":{\"type\":\"Plain\",\"value\":{\"type\":\"__fluid_handle__\",\"url\":\"/defaultComponent/c6863402-5e81-45ac-83f3-03410e959604\"}},\"styleRegistryStyleHeading 2\":{\"type\":\"Plain\",\"value\":{\"type\":\"__fluid_handle__\",\"url\":\"/defaultComponent/115d8655-0c3c-43d2-a15f-52d77fd3c918\"}},\"styleRegistryStyleBody\":{\"type\":\"Plain\",\"value\":{\"type\":\"__fluid_handle__\",\"url\":\"/defaultComponent/a9534c76-92ce-41d2-8682-586a4c1122ba\"}},\"styleRegistryStyleStrong\":{\"type\":\"Plain\",\"value\":{\"type\":\"__fluid_handle__\",\"url\":\"/defaultComponent/ccb9d801-45c5-4f53-8a55-841ae9ffc63f\"}},\"styleRegistryStyleEmphasis\":{\"type\":\"Plain\",\"value\":{\"type\":\"__fluid_handle__\",\"url\":\"/defaultComponent/a0284d80-3d0b-4f31-8e8b-1714c0aa1076\"}},\"styleRegistryStyleTitle\":{\"type\":\"Plain\",\"value\":{\"type\":\"__fluid_handle__\",\"url\":\"/defaultComponent/e3aaafa2-00ea-4b63-a6c8-79605b625b08\"}},\"styleRegistryStyleFixed Table\":{\"type\":\"Plain\",\"value\":{\"type\":\"__fluid_handle__\",\"url\":\"/defaultComponent/0e81569f-f59f-4102-b69e-8bfcf5e2301e\"}}}}",
                      "encoding": "utf-8"
                    }
                  }
                ]
              },
              "mode": "040000",
              "type": "Tree"
            },
            {
              "path": "f4c3d94a-653d-4bb3-86cf-a0e9db67ab17",
              "value": {
                "entries": [
                  {
                    "path": ".attributes",
                    "mode": "100644",
                    "type": "Blob",
                    "value": {
                      "contents": "{\"type\":\"https://graph.microsoft.com/types/map\",\"snapshotFormatVersion\":\"0.2\",\"packageVersion\":\"0.35.0\"}",
                      "encoding": "utf-8"
                    }
                  },
                  {
                    "path": "header",
                    "mode": "100644",
                    "type": "Blob",
                    "value": {
                      "contents": "{\"blobs\":[],\"content\":{\"ItemType\":{\"type\":\"Plain\",\"value\":\"Style\"},\"name\":{\"type\":\"Plain\",\"value\":\"Heading 2\"},\"styleTarget\":{\"type\":\"Plain\",\"value\":\"paragraph\"},\"propertiesfontName\":{\"type\":\"Plain\",\"value\":\"Segoe UI\"},\"propertiesbold\":{\"type\":\"Plain\",\"value\":true},\"propertiesfontSize\":{\"type\":\"Plain\",\"value\":18},\"propertiesfontColor\":{\"type\":\"Plain\",\"value\":\"#484644\"},\"propertiespaddingBottom\":{\"type\":\"Plain\",\"value\":15},\"propertiespaddingTop\":{\"type\":\"Plain\",\"value\":12},\"propertiesrole\":{\"type\":\"Plain\",\"value\":\"heading\"},\"propertiesariaLevel\":{\"type\":\"Plain\",\"value\":\"2\"},\"propertiestabIndex\":{\"type\":\"Plain\",\"value\":-1},\"propertiesoutline\":{\"type\":\"Plain\",\"value\":\"none\"}}}",
                      "encoding": "utf-8"
                    }
                  }
                ]
              },
              "mode": "040000",
              "type": "Tree"
            },
            {
              "path": "fd7a8855-78e2-49bb-9a00-f13f60687268",
              "value": {
                "entries": [
                  {
                    "path": ".attributes",
                    "mode": "100644",
                    "type": "Blob",
                    "value": {
                      "contents": "{\"type\":\"https://graph.microsoft.com/types/map\",\"snapshotFormatVersion\":\"0.2\",\"packageVersion\":\"0.35.0\"}",
                      "encoding": "utf-8"
                    }
                  },
                  {
                    "path": "header",
                    "mode": "100644",
                    "type": "Blob",
                    "value": {
                      "contents": "{\"blobs\":[],\"content\":{}}",
                      "encoding": "utf-8"
                    }
                  }
                ]
              },
              "mode": "040000",
              "type": "Tree"
            },
            {
              "path": "gc",
              "mode": "100644",
              "type": "Blob",
              "value": {
                "contents": "{\"usedRoutes\":[\"\"],\"gcData\":{\"gcNodes\":{\"/root\":[\"/defaultComponent/3628d460-1875-4be9-a2be-a64320d66221\",\"/defaultComponent/fd7a8855-78e2-49bb-9a00-f13f60687268\",\"/defaultComponent/1c868c2e-38a9-4c69-bd74-a461e644ecb6\",\"/defaultComponent/e9530f65-4ea9-4c74-8724-b888bd929c65\",\"/defaultComponent/179fb24a-1187-45eb-8330-5c3e3b6b2598\",\"/defaultComponent\"],\"/3628d460-1875-4be9-a2be-a64320d66221\":[\"/defaultComponent\"],\"/fd7a8855-78e2-49bb-9a00-f13f60687268\":[\"/defaultComponent\"],\"/219bc753-71a8-43ee-aed4-8a71ae7eee46\":[\"/defaultComponent\"],\"/1c868c2e-38a9-4c69-bd74-a461e644ecb6\":[\"/defaultComponent/219bc753-71a8-43ee-aed4-8a71ae7eee46\",\"/defaultComponent\"],\"/87d1481d-e476-43ec-8639-a271dafcf616\":[\"/defaultComponent/b17a1b79-4a9c-4711-a91a-e9b738967d41\",\"/defaultComponent/f4c3d94a-653d-4bb3-86cf-a0e9db67ab17\",\"/defaultComponent/c896c5c1-e463-44ac-ac8f-f8ad8ac218c4\",\"/defaultComponent/4acc1217-7bad-472d-892c-f691e5e38795\",\"/defaultComponent/031285c0-a9f4-4f3c-b78f-cf6d90cc374c\",\"/defaultComponent/8204010d-bf9c-4bf6-a9bd-eccdda2d5501\",\"/defaultComponent/c9bcf798-0f35-4a67-87be-6dd269749857\",\"/defaultComponent\"],\"/b17a1b79-4a9c-4711-a91a-e9b738967d41\":[\"/defaultComponent\"],\"/f4c3d94a-653d-4bb3-86cf-a0e9db67ab17\":[\"/defaultComponent\"],\"/c896c5c1-e463-44ac-ac8f-f8ad8ac218c4\":[\"/defaultComponent\"],\"/4acc1217-7bad-472d-892c-f691e5e38795\":[\"/defaultComponent\"],\"/031285c0-a9f4-4f3c-b78f-cf6d90cc374c\":[\"/defaultComponent\"],\"/8204010d-bf9c-4bf6-a9bd-eccdda2d5501\":[\"/defaultComponent\"],\"/c9bcf798-0f35-4a67-87be-6dd269749857\":[\"/defaultComponent\"],\"/e9530f65-4ea9-4c74-8724-b888bd929c65\":[\"/defaultComponent/c6863402-5e81-45ac-83f3-03410e959604\",\"/defaultComponent/115d8655-0c3c-43d2-a15f-52d77fd3c918\",\"/defaultComponent/a9534c76-92ce-41d2-8682-586a4c1122ba\",\"/defaultComponent/ccb9d801-45c5-4f53-8a55-841ae9ffc63f\",\"/defaultComponent/a0284d80-3d0b-4f31-8e8b-1714c0aa1076\",\"/defaultComponent/e3aaafa2-00ea-4b63-a6c8-79605b625b08\",\"/defaultComponent/0e81569f-f59f-4102-b69e-8bfcf5e2301e\",\"/defaultComponent\"],\"/c6863402-5e81-45ac-83f3-03410e959604\":[\"/defaultComponent\"],\"/115d8655-0c3c-43d2-a15f-52d77fd3c918\":[\"/defaultComponent\"],\"/a9534c76-92ce-41d2-8682-586a4c1122ba\":[\"/defaultComponent\"],\"/ccb9d801-45c5-4f53-8a55-841ae9ffc63f\":[\"/defaultComponent\"],\"/a0284d80-3d0b-4f31-8e8b-1714c0aa1076\":[\"/defaultComponent\"],\"/e3aaafa2-00ea-4b63-a6c8-79605b625b08\":[\"/defaultComponent\"],\"/0e81569f-f59f-4102-b69e-8bfcf5e2301e\":[\"/defaultComponent\"],\"/179fb24a-1187-45eb-8330-5c3e3b6b2598\":[\"/defaultComponent/90e448c6-8d29-4e56-bf6d-126423b700a5\",\"/defaultComponent/23785c73-3f07-4064-8505-5f3ea078a3f3\",\"/defaultComponent/7af81df4-4161-4438-ab89-a68863b3cd1d\",\"/defaultComponent\"],\"/90e448c6-8d29-4e56-bf6d-126423b700a5\":[\"/defaultComponent\"],\"/23785c73-3f07-4064-8505-5f3ea078a3f3\":[\"/defaultComponent\"],\"/7af81df4-4161-4438-ab89-a68863b3cd1d\":[\"/defaultComponent\"],\"/\":[\"/defaultComponent/root\",\"/defaultComponent/3628d460-1875-4be9-a2be-a64320d66221\",\"/defaultComponent/fd7a8855-78e2-49bb-9a00-f13f60687268\",\"/defaultComponent/219bc753-71a8-43ee-aed4-8a71ae7eee46\",\"/defaultComponent/1c868c2e-38a9-4c69-bd74-a461e644ecb6\",\"/defaultComponent/87d1481d-e476-43ec-8639-a271dafcf616\",\"/defaultComponent/b17a1b79-4a9c-4711-a91a-e9b738967d41\",\"/defaultComponent/f4c3d94a-653d-4bb3-86cf-a0e9db67ab17\",\"/defaultComponent/c896c5c1-e463-44ac-ac8f-f8ad8ac218c4\",\"/defaultComponent/4acc1217-7bad-472d-892c-f691e5e38795\",\"/defaultComponent/031285c0-a9f4-4f3c-b78f-cf6d90cc374c\",\"/defaultComponent/8204010d-bf9c-4bf6-a9bd-eccdda2d5501\",\"/defaultComponent/c9bcf798-0f35-4a67-87be-6dd269749857\",\"/defaultComponent/e9530f65-4ea9-4c74-8724-b888bd929c65\",\"/defaultComponent/c6863402-5e81-45ac-83f3-03410e959604\",\"/defaultComponent/115d8655-0c3c-43d2-a15f-52d77fd3c918\",\"/defaultComponent/a9534c76-92ce-41d2-8682-586a4c1122ba\",\"/defaultComponent/ccb9d801-45c5-4f53-8a55-841ae9ffc63f\",\"/defaultComponent/a0284d80-3d0b-4f31-8e8b-1714c0aa1076\",\"/defaultComponent/e3aaafa2-00ea-4b63-a6c8-79605b625b08\",\"/defaultComponent/0e81569f-f59f-4102-b69e-8bfcf5e2301e\",\"/defaultComponent/179fb24a-1187-45eb-8330-5c3e3b6b2598\",\"/defaultComponent/90e448c6-8d29-4e56-bf6d-126423b700a5\",\"/defaultComponent/23785c73-3f07-4064-8505-5f3ea078a3f3\",\"/defaultComponent/7af81df4-4161-4438-ab89-a68863b3cd1d\"]}}}",
                "encoding": "utf-8"
              }
            },
            {
              "path": "root",
              "value": {
                "entries": [
                  {
                    "path": ".attributes",
                    "mode": "100644",
                    "type": "Blob",
                    "value": {
                      "contents": "{\"type\":\"https://graph.microsoft.com/types/map\",\"snapshotFormatVersion\":\"0.2\",\"packageVersion\":\"0.35.0\"}",
                      "encoding": "utf-8"
                    }
                  },
                  {
                    "path": "header",
                    "mode": "100644",
                    "type": "Blob",
                    "value": {
                      "contents": "{\"blobs\":[],\"content\":{\"presence\":{\"type\":\"Plain\",\"value\":{\"type\":\"__fluid_handle__\",\"url\":\"/defaultComponent/3628d460-1875-4be9-a2be-a64320d66221\"}},\"language\":{\"type\":\"Plain\",\"value\":{\"type\":\"__fluid_handle__\",\"url\":\"/defaultComponent/fd7a8855-78e2-49bb-9a00-f13f60687268\"}},\"text\":{\"type\":\"Plain\",\"value\":{\"type\":\"__fluid_handle__\",\"url\":\"/defaultComponent/1c868c2e-38a9-4c69-bd74-a461e644ecb6\"}},\"text.ItemType\":{\"type\":\"Plain\",\"value\":\"StoryNode\"},\"endOfKeys\":{\"type\":\"Plain\",\"value\":true},\"text.documentStyleRegistry\":{\"type\":\"Plain\",\"value\":{\"type\":\"__fluid_handle__\",\"url\":\"/defaultComponent/e9530f65-4ea9-4c74-8724-b888bd929c65\"}},\"text.documentListRegistry\":{\"type\":\"Plain\",\"value\":{\"type\":\"__fluid_handle__\",\"url\":\"/defaultComponent/179fb24a-1187-45eb-8330-5c3e3b6b2598\"}}}}",
                      "encoding": "utf-8"
                    }
                  }
                ]
              },
              "mode": "040000",
              "type": "Tree"
            }
          ]
        },
        "mode": "040000",
        "type": "Tree"
      },
      {
        "path": "discover",
        "value": {
          "entries": [
            {
              "path": ".component",
              "mode": "100644",
              "type": "Blob",
              "value": {
                "contents": "{\"pkg\":\"[\\\"@ms/discover\\\"]\",\"snapshotFormatVersion\":\"0.1\",\"isRootDataStore\":true}",
                "encoding": "utf-8"
              }
            },
            {
              "path": "gc",
              "mode": "100644",
              "type": "Blob",
              "value": {
                "contents": "{\"usedRoutes\":[\"\"],\"gcData\":{\"gcNodes\":{\"/\":[]}}}",
                "encoding": "utf-8"
              }
            }
          ]
        },
        "mode": "040000",
        "type": "Tree"
      },
      {
        "mode": "100644",
        "path": "quorumMembers",
        "type": "Blob",
        "value": {
          "contents": "[[\"d7e3c1a2-4d06-49cd-bc4f-e889fdd47524\",{\"client\":{\"user\":{\"id\":\"akp55qhuq@example.com}\",\"name\":\"v0yi3efr1s3nu7s\",\"email\":\"2meqtuajt@example.com}\"}},\"sequenceNumber\":2996}]]",
          "encoding": "utf-8"
        }
      },
      {
        "mode": "100644",
        "path": "quorumProposals",
        "type": "Blob",
        "value": {
          "contents": "[]",
          "encoding": "utf-8"
        }
      },
      {
        "mode": "100644",
        "path": "quorumValues",
        "type": "Blob",
        "value": {
          "contents": "[[\"code\",{\"approvalSequenceNumber\":3,\"commitSequenceNumber\":-1,\"key\":\"code\",\"sequenceNumber\":2,\"value\":{\"package\":\"@ms/office-fluid-container\"}}]]",
          "encoding": "utf-8"
        }
      },
      {
        "path": "registro",
        "value": {
          "entries": [
            {
              "path": ".component",
              "mode": "100644",
              "type": "Blob",
              "value": {
                "contents": "{\"pkg\":\"[\\\"@ms/registro\\\"]\",\"snapshotFormatVersion\":\"0.1\",\"isRootDataStore\":true}",
                "encoding": "utf-8"
              }
            },
            {
              "path": "gc",
              "mode": "100644",
              "type": "Blob",
              "value": {
                "contents": "{\"usedRoutes\":[\"\"],\"gcData\":{\"gcNodes\":{\"/\":[]}}}",
                "encoding": "utf-8"
              }
            }
          ]
        },
        "mode": "040000",
        "type": "Tree"
      }
    ]
  },
  "commits": {}
}
